[
  {
    "data": "即事五言絶春畫七言絶春夜野寺海朝懷古七言",
    "bbox": [
      1547.004,
      633.607,
      1674.98,
      2488.556
    ],
    "confidence": 0.8656298275476852,
    "page": 59,
    "column_order": 0,
    "engine": "Surya_v0.20"
  },
  {
    "data": "安于江五言絶龍洞寺七言律德江懷古七言律",
    "bbox": [
      1400.208,
      633.607,
      1528.1840000000002,
      2402.546
    ],
    "confidence": 0.8656298275476852,
    "page": 59,
    "column_order": 1,
    "engine": "Surya_v0.20"
  },
  {
    "data": "浮石渡六言律樑特以神符港口留別北城",
    "bbox": [
      1262.8220000000001,
      633.607,
      1388.916,
      2488.556
    ],
    "confidence": 0.8656298275476852,
    "page": 59,
    "column_order": 2,
    "engine": "Surya_v0.20"
  },
  {
    "data": "珠橋過雨二首七言律維先道中登浴翠山七言律",
    "bbox": [
      1112.262,
      633.607,
      1238.356,
      2488.556
    ],
    "confidence": 0.8656298275476852,
    "page": 59,
    "column_order": 3,
    "engine": "Surya_v0.20"
  },
  {
    "data": "青巖渡三疊山七言絶觀巨慶有感",
    "bbox": [
      971.1120000000001,
      633.607,
      1095.3239999999998,
      2213.324
    ],
    "confidence": 0.8656298275476852,
    "page": 59,
    "column_order": 4,
    "engine": "Surya_v0.20"
  },
  {
    "data": "賦得千里驛亭逢苦雨客中九重永誓有懷",
    "bbox": [
      824.316,
      633.607,
      950.41,
      2500.024
    ],
    "confidence": 0.8656298275476852,
    "page": 59,
    "column_order": 5,
    "engine": "Surya_v0.20"
  },
  {
    "data": "永江月夜七言律秣營懷古續泉七言絶",
    "bbox": [
      681.284,
      633.607,
      809.26,
      2488.556
    ],
    "confidence": 0.8656298275476852,
    "page": 59,
    "column_order": 6,
    "engine": "Surya_v0.20"
  },
  {
    "data": "旅次憶諸兒江卅勝景題為武穆廟",
    "bbox": [
      530.7239999999999,
      633.607,
      658.6999999999999,
      2201.856
    ],
    "confidence": 0.8656298275476852,
    "page": 59,
    "column_order": 7,
    "engine": "Surya_v0.20"
  },
  {
    "data": "江卅旅次馬當勝覓影石懷青蓮遊龍山",
    "bbox": [
      385.81,
      633.607,
      513.7860000000001,
      2488.556
    ],
    "confidence": 0.8656298275476852,
    "page": 59,
    "column_order": 8,
    "engine": "Surya_v0.20"
  },
  {
    "data": "下十詩",
    "bbox": [
      310.53000000000003,
      831.43,
      348.17,
      1103.795
    ],
    "confidence": 0.8656298275476852,
    "page": 59,
    "column_order": 9,
    "engine": "Surya_v0.20"
  },
  {
    "data": "阮忠彦 介軒詩集",
    "bbox": [
      122.33,
      438.651,
      173.144,
      745.4200000000001
    ],
    "confidence": 0.8656298275476852,
    "page": 59,
    "column_order": 10,
    "engine": "Surya_v0.20"
  },
  {
    "data": "一九",
    "bbox": [
      122.33,
      2379.6099999999997,
      173.144,
      2454.152
    ],
    "confidence": 0.8656298275476852,
    "page": 59,
    "column_order": 11,
    "engine": "Surya_v0.20"
  }
]
