[
  {
    "text": "臺清琴鶴齋。匆忙羈子幸趨庭。",
    "bbox": [
      1304.9250000000002,
      607.804,
      1438.275,
      1671.4609999999998
    ],
    "confidence": 0.8379412456004716,
    "page": 352,
    "column_order": 0,
    "engine": "Surya_v0.20"
  },
  {
    "text": "久以寧城子累。",
    "bbox": [
      1190.625,
      711.016,
      1304.9250000000002,
      1221.3419999999999
    ],
    "confidence": 0.8379412456004716,
    "page": 352,
    "column_order": 1,
    "engine": "Surya_v0.20"
  },
  {
    "text": "城有蕭園老塔。潘進士故宅天寧寺。",
    "bbox": [
      1242.06,
      1238.544,
      1323.975,
      2078.575
    ],
    "confidence": 0.8379412456004716,
    "page": 352,
    "column_order": 2,
    "engine": "Surya_v0.20"
  },
  {
    "text": "笑我無心客。亦無山溪恋我泊。邕州乘城人似凌空鳥。泛",
    "bbox": [
      1061.085,
      619.272,
      1190.625,
      2508.625
    ],
    "confidence": 0.8379412456004716,
    "page": 352,
    "column_order": 3,
    "engine": "Surya_v0.20"
  },
  {
    "text": "碧帆如赴敵。騎蕭塔雲回。苔意古。潘軒月過竹情秋。可怜",
    "bbox": [
      937.26,
      619.272,
      1061.085,
      2508.625
    ],
    "confidence": 0.8379412456004716,
    "page": 352,
    "column_order": 4,
    "engine": "Surya_v0.20"
  },
  {
    "text": "夜半鐘聲落。獨起掀篷整荆縷。",
    "bbox": [
      817.245,
      619.272,
      937.26,
      1671.4609999999998
    ],
    "confidence": 0.8379412456004716,
    "page": 352,
    "column_order": 5,
    "engine": "Surya_v0.20"
  },
  {
    "text": "南寧換船適。遇倫弊不寧。且舟夫亂棹坐。臥危困。",
    "bbox": [
      699.135,
      711.016,
      817.245,
      2336.605
    ],
    "confidence": 0.8379412456004716,
    "page": 352,
    "column_order": 6,
    "engine": "Surya_v0.20"
  },
  {
    "text": "因思",
    "bbox": [
      699.135,
      2336.605,
      817.245,
      2508.625
    ],
    "confidence": 0.8379412456004716,
    "page": 352,
    "column_order": 7,
    "engine": "Surya_v0.20"
  },
  {
    "text": "宵寐江塘一線通。寧城牌下換倫蓬。應庭似覆竿頭上。喧",
    "bbox": [
      565.785,
      619.272,
      699.135,
      2508.625
    ],
    "confidence": 0.8379412456004716,
    "page": 352,
    "column_order": 8,
    "engine": "Surya_v0.20"
  },
  {
    "text": "沸如行電雨。中眼度居昏。千里碧夢馳。勾滿一輪紅。不遑",
    "bbox": [
      436.245,
      619.272,
      565.785,
      2508.625
    ],
    "confidence": 0.8379412456004716,
    "page": 352,
    "column_order": 9,
    "engine": "Surya_v0.20"
  },
  {
    "text": "丁儒完 默翁使集",
    "bbox": [
      30.48,
      444.385,
      80.01,
      748.287
    ],
    "confidence": 0.8379412456004716,
    "page": 352,
    "column_order": 10,
    "engine": "Surya_v0.20"
  },
  {
    "text": "三二三",
    "bbox": [
      49.53,
      2359.5409999999997,
      97.15499999999999,
      2479.955
    ],
    "confidence": 0.8379412456004716,
    "page": 352,
    "column_order": 11,
    "engine": "Surya_v0.20"
  }
]