[
  {
    "text": "越南漢文典行文獻集成(越南所藏編)",
    "bbox": [
      1815.465,
      427.183,
      1864.995,
      1020.6519999999999
    ],
    "confidence": 0.8265249566322687,
    "page": 243,
    "column_order": 0,
    "engine": "Surya_v0.20"
  },
  {
    "text": "〇四",
    "bbox": [
      1815.465,
      2379.6099999999997,
      1864.995,
      2465.62
    ],
    "confidence": 0.8265249566322687,
    "page": 243,
    "column_order": 1,
    "engine": "Surya_v0.20"
  },
  {
    "text": "釋和",
    "bbox": [
      1596.3899999999999,
      759.755,
      1649.73,
      934.642
    ],
    "confidence": 0.8265249566322687,
    "page": 243,
    "column_order": 2,
    "engine": "Surya_v0.20"
  },
  {
    "text": "生尚有咸漁父扁舟樵千担黃骨戴月戴星師",
    "bbox": [
      1443.99,
      573.4,
      1571.625,
      2425.482
    ],
    "confidence": 0.8265249566322687,
    "page": 243,
    "column_order": 3,
    "engine": "Surya_v0.20"
  },
  {
    "text": "登揚桐公祠堂",
    "bbox": [
      1310.6399999999999,
      845.765,
      1434.465,
      1436.367
    ],
    "confidence": 0.8265249566322687,
    "page": 243,
    "column_order": 4,
    "engine": "Surya_v0.20"
  },
  {
    "text": "近水樓臺先得月向陽花草易為春古聞此語從稱誦令見江西第一人",
    "bbox": [
      1028.7,
      653.676,
      1291.5900000000001,
      2491.423
    ],
    "confidence": 0.8265249566322687,
    "page": 243,
    "column_order": 5,
    "engine": "Surya_v0.20"
  },
  {
    "text": "到南京城在應天府上元縣江陵縣大勝驛",
    "bbox": [
      899.16,
      851.4989999999999,
      1019.1750000000001,
      2517.226
    ],
    "confidence": 0.8265249566322687,
    "page": 243,
    "column_order": 6,
    "engine": "Surya_v0.20"
  },
  {
    "text": "餘腥一駕到南京線緲仙都苑上清銀漢槎模牛",
    "bbox": [
      765.8100000000001,
      656.543,
      885.825,
      2517.226
    ],
    "confidence": 0.8265249566322687,
    "page": 243,
    "column_order": 7,
    "engine": "Surya_v0.20"
  },
  {
    "text": "斗次王街樓拂疊教多編鞍室馬人拖紫帽蓋書",
    "bbox": [
      619.125,
      656.543,
      741.0450000000001,
      2497.157
    ],
    "confidence": 0.8265249566322687,
    "page": 243,
    "column_order": 8,
    "engine": "Surya_v0.20"
  },
  {
    "text": "半客蔬瓊對酒一卮詩八首酣教聖世詠昇平",
    "bbox": [
      480.06,
      656.543,
      601.98,
      2405.413
    ],
    "confidence": 0.8265249566322687,
    "page": 243,
    "column_order": 9,
    "engine": "Surya_v0.20"
  },
  {
    "text": "壽號都督初慶詩曰",
    "bbox": [
      358.14,
      851.4989999999999,
      476.25,
      1616.9879999999998
    ],
    "confidence": 0.8265249566322687,
    "page": 243,
    "column_order": 10,
    "engine": "Surya_v0.20"
  }
]